Metadata-Version: 1.0
Name: pychromaprint
Version: 1.2.2
Summary: Python bindings for Chromaprint acoustic fingerprinting library
Home-page: UNKNOWN
Author: UNKNOWN
Author-email: UNKNOWN
License: UNKNOWN
Platform: UNKNOWN
